{
  "report_version": "1.0",
  "generated_at": "2026-07-23T08:35:05.778436Z",
  "feed_generated_at": "2026-07-22T19:46:07.202977Z",
  "feed_version": "3.8",
  "status": "passed",
  "errors": [],
  "warnings": [
    "Phase 5 target: ZA concentration is 66.9%; target maximum is 55%"
  ],
  "metrics": {
    "opportunity_count": 1540,
    "by_region": {
      "Southern Africa": 1069,
      "Central Africa": 17,
      "West Africa": 107,
      "East Africa": 110,
      "Non-Africa": 1,
      "North Africa": 16,
      "unknown": 215,
      "Africa": 5
    },
    "by_country_code": {
      "AO": 1,
      "BW": 3,
      "CD": 4,
      "SN": 10,
      "CM": 4,
      "KE": 51,
      "CI": 11,
      "US": 1,
      "EG": 4,
      "TZ": 23,
      "UG": 6,
      "BI": 7,
      "ET": 3,
      "ZA": 1031,
      "NG": 58,
      "SL": 2,
      "RW": 15,
      "LR": 1,
      "MZ": 11,
      "GN": 1,
      "location_neutral": 27,
      "official_location_pending": 193,
      "MG": 5,
      "MA": 12,
      "unknown": 2,
      "ZM": 18,
      "BJ": 22,
      "MW": 4,
      "GA": 7,
      "TG": 2,
      "GQ": 1
    },
    "physical_country_records": 1318,
    "location_neutral_records": 27,
    "location_neutral_percent": 1.8,
    "official_location_pending_records": 193,
    "official_location_pending_percent": 12.5,
    "unresolved_location_records": 2,
    "unresolved_location_percent": 0.1,
    "by_source": {
      "Cornerstone-hosted institutional board": 27,
      "PageUp-hosted institutional board": 16,
      "DFI and multilateral official career page": 21,
      "NGO and UN official career page": 3,
      "Kenya public institution official vacancies": 12,
      "Multinational employer official careers": 124,
      "Kenya Public Service Commission official vacancies": 18,
      "Tanzania PSRS official advertisements": 3,
      "South Africa DPSA official vacancy circular": 613,
      "Adzuna": 404,
      "One Acre Fund": 33,
      "Acumen": 2,
      "GiveDirectly": 9,
      "Stripe": 7,
      "GitLab": 1,
      "Ramp": 48,
      "PostHog": 5,
      "Copia Global": 1,
      "Sun King": 151,
      "Médecins Sans Frontières International": 2,
      "MSF West and Central Africa": 9,
      "Nawiri Group": 8,
      "MCD Global Health": 1,
      "Himalayas": 8,
      "Remotive": 10,
      "Jobicy": 3,
      "RemoteOK": 1
    },
    "official_apply_records": 1114,
    "official_apply_percent": 72.3
  }
}
