{
  "report_version": "1.0",
  "generated_at": "2026-07-24T13:50:25.048099Z",
  "feed_generated_at": "2026-07-24T08:50:40.701965Z",
  "feed_version": "3.8",
  "summary": {
    "opportunity_count": 1533,
    "government_opportunity_count": 644,
    "phase9_priority_opportunity_count": 632,
    "represented_portals": 6,
    "represented_countries": 5,
    "with_advert_reference_count": 632,
    "with_deadline_count": 60,
    "with_number_of_positions_count": 19
  },
  "coverage": {
    "by_country": {
      "South Africa": 604,
      "Kenya": 20,
      "unknown": 10,
      "Zambia": 6,
      "Benin": 3,
      "Tanzania": 1
    },
    "by_portal": {
      "South Africa Department of Public Service and Administration": 613,
      "Kenya Public Service Commission": 18,
      "Kenya Broadcasting Corporation": 10,
      "Egerton University": 1,
      "Kenya Railways Corporation": 1,
      "Tanzania Public Service Recruitment Secretariat": 1
    },
    "by_public_service_grade": {
      "unknown": 626,
      "CSG 8": 6,
      "E": 4,
      "CSG 9": 3,
      "CSG 11": 2,
      "CSG 10": 1,
      "CSG 12": 1,
      "Not Defined": 1
    },
    "by_role_family": {
      "humanitarian": 89,
      "development_programmes": 77,
      "technology": 75,
      "government_administration": 48,
      "human_resources": 43,
      "health": 39,
      "operations": 36,
      "agriculture": 33,
      "investment": 30,
      "risk_and_compliance": 22,
      "logistics": 17,
      "banking_and_finance": 16,
      "engineering": 15,
      "monitoring_evaluation_and_learning": 15,
      "economics_and_research": 13,
      "education": 13,
      "administration": 9,
      "legal": 9,
      "public_policy": 9,
      "skilled_trades": 9,
      "marketing_communications": 6,
      "unknown": 6,
      "real_estate": 4,
      "procurement": 3,
      "sales_business_development": 3,
      "hospitality": 2,
      "customer_operations": 1,
      "energy": 1,
      "esg_and_safeguards": 1
    }
  }
}
